SMComPy.cp39-win_amd64.pyd
SMComPy-1.0.4.dist-info/LICENSE
SMComPy-1.0.4.dist-info/METADATA
SMComPy-1.0.4.dist-info/WHEEL
SMComPy-1.0.4.dist-info/top_level.txt
SMComPy-1.0.4.dist-info/RECORD
