Metadata-Version: 2.1
Name: SMComPy
Version: 1.0.4
Summary: SMComPy project
Home-page: https://github.com/sensemore/SMCom
Author: sensemore
Author-email: hello@sensemore.io
License: MIT
Project-URL: Bug Reports, https://github.com/sensemore/SMCom/issues
Project-URL: Source, https://github.com/sensemore/SMCom
Keywords: SMCom,sensemore,communication protocol,uart communication protocol,serial communication protocol
Platform: UNKNOWN
Requires-Python: >=3.6
License-File: LICENSE
Requires-Dist: pybind11 (==2.7.0)
